sap2assembler/__init__.py
sap2assembler/__main__.py
sap2assembler/assembler.py
sap2assembler-4.0.2.dist-info/licenses/LICENSE.txt
sap2assembler-4.0.2.dist-info/METADATA
sap2assembler-4.0.2.dist-info/WHEEL
sap2assembler-4.0.2.dist-info/entry_points.txt
sap2assembler-4.0.2.dist-info/top_level.txt
sap2assembler-4.0.2.dist-info/RECORD
