Metadata-Version: 2.4
Name: sap2assembler
Version: 4.0.2
Summary: A simple assembler for the SAP-2 computer architecture.
Home-page: https://github.com/samTheComputerArchitect/sap2assembler
Author: Samarth Javagal
Author-email: samarthjavagal@gmail.com
Classifier: Programming Language :: Python :: 3
Classifier: License :: OSI Approved :: MIT License
Classifier: Operating System :: OS Independent
Requires-Python: >=3.6
License-File: LICENSE.txt
Dynamic: author
Dynamic: author-email
Dynamic: classifier
Dynamic: description
Dynamic: description-content-type
Dynamic: home-page
Dynamic: license-file
Dynamic: requires-python
Dynamic: summary
